myob/__init__.py
myob/api.py
myob/constants.py
myob/credentials.py
myob/endpoints.py
myob/exceptions.py
myob/managers.py
myob/types.py
myob/utils.py
pymyob-1.4.0.dist-info/METADATA
pymyob-1.4.0.dist-info/WHEEL
pymyob-1.4.0.dist-info/licenses/LICENSE
pymyob-1.4.0.dist-info/RECORD
