Metadata-Version: 2.3
Name: pymyob
Version: 1.4.0
Summary: A Python SDK for the MYOB Business (formerly AccountRight Live, and New Essentials) API.
Project-URL: source, https://github.com/uptick/pymyob
Project-URL: releasenotes, https://github.com/uptick/pymyob/releases
Author-email: Jarek Głowacki <jarekwg@gmail.com>
Maintainer-email: Jarek Głowacki <jarekwg@gmail.com>
Keywords: myob
Classifier: Development Status :: 5 - Production/Stable
Classifier: Environment :: Web Environment
Classifier: Intended Audience :: Developers
Classifier: License :: OSI Approved :: BSD License
Classifier: Operating System :: OS Independent
Classifier: Programming Language :: Python
Classifier: Programming Language :: Python :: 3
Classifier: Topic :: Office/Business :: Financial :: Accounting
Requires-Python: >=3.10
Requires-Dist: requests-oauthlib>=2.0.0
Requires-Dist: requests>=2.32.0
